comfyui_tooling_nodes/.gitignore
comfyui_tooling_nodes/LICENSE
comfyui_tooling_nodes/__init__.py
comfyui_tooling_nodes/api.py
comfyui_tooling_nodes/nodes.py
comfyui_tooling_nodes/pyproject.toml
comfyui_tooling_nodes-0.1.0.dist-info/METADATA
comfyui_tooling_nodes-0.1.0.dist-info/WHEEL
comfyui_tooling_nodes-0.1.0.dist-info/entry_points.txt
comfyui_tooling_nodes-0.1.0.dist-info/licenses/LICENSE
comfyui_tooling_nodes-0.1.0.dist-info/RECORD
