Metadata-Version: 2.1
Name: comfyui-tooling-nodes
Version: 0.1.0
Project-URL: Homepage, https://github.com/Acly/comfyui-tooling-nodes
Project-URL: comfyui-legacy, https://github.com/Chaoses-Ib/comfyui-legacy
License-File: LICENSE
Keywords: comfyui
